Lab1/Lab1_multiplexor/mux_Nto1.v
module mux_Nto1 #(parameter N = 5) (
    input [N-1:0] vec,
    input [15:0] addr,

    output wire res
);

assign res = vec[addr];

endmodule

Lab1/Lab1_multiplexor/mux_Nto1_tb.v
`include "mux_Nto1.v"
`timescale 1ps/1ps

module mux_Nto1_tb ();

reg [6:0] test_vec = 0;
reg [15:0] addr = 0;
wire out;
integer i;

mux_Nto1 #(.N(7)) mux_7to1 (.vec(test_vec), .addr(addr), .res(out));

initial begin
    $dumpvars;

    for(i = 0; i < 7; i = i+1)begin
        #10
        test_vec = 7'h0;
        test_vec[i] = 1;
        addr = i;
    end
    #10
    $finish;
end

endmodule

Lab1/Lab1_multiplexor/dump.vcd
$date
	Wed Oct 25 12:36:37 2023
$end
$version
	Icarus Verilog
$end
$timescale
	1ps
$end
$scope module mux_Nto1_tb $end
$var wire 1 ! out $end
$var reg 16 " addr [15:0] $end
$var reg 7 # test_vec [6:0] $end
$var integer 32 $ i [31:0] $end
$scope module mux_7to1 $end
$var wire 16 % addr [15:0] $end
$var wire 7 & vec [6:0] $end
$var wire 1 ! res $end
$upscope $end
$upscope $end
$enddefinitions $end
#0
$dumpvars
b0 &
b0 %
b0 $
b0 #
b0 "
0!
$end
#10
b1 $
1!
b1 #
b1 &
#20
b10 $
b1 "
b1 %
1!
b10 #
b10 &
#30
b11 $
b10 "
b10 %
1!
b100 #
b100 &
#40
b100 $
b11 "
b11 %
1!
b1000 #
b1000 &
#50
b101 $
b100 "
b100 %
1!
b10000 #
b10000 &
#60
b110 $
b101 "
b101 %
1!
b100000 #
b100000 &
#70
b111 $
b110 "
b110 %
1!
b1000000 #
b1000000 &
